setup.py
hive/__init__.py
hive/cmd.py
hive/config.py
hive/log.py
hive/main.py
hive/task.py
hive/src/__init__.py
hive/src/env.py
hive/src/func.py
hive/src/obj.py
hive/src/task.py
hive_c.egg-info/PKG-INFO
hive_c.egg-info/SOURCES.txt
hive_c.egg-info/dependency_links.txt
hive_c.egg-info/entry_points.txt
hive_c.egg-info/not-zip-safe
hive_c.egg-info/requires.txt
hive_c.egg-info/top_level.txt